{
    "diagnostic.displayByAle": true,
    "git.enableGutters": false,
    // "git.addedSign.hlGroup": "GitAdd",
    // "git.changedSign.hlGroup": "GitChange",
    // "git.removedSign.hlGroup": "GitDelete",
    // "git.topRemovedSign.hlGroup": "GitDelete",
    // "git.changeRemovedSign.hlGroup": "GitChangeDelete",
    // "git.addedSign.text": "+",
    // "git.changedSign.text": "~",
    // "git.removedSign.text": "-",
    // "git.changeRemovedSign.text": "~",
    "languageserver": {
        "bash": {
          "command": "bash-language-server",
          "args": ["start"],
          "filetypes": ["sh"],
          "ignoredRootPaths": ["~"]
        }
      }
}
